two_fast_auth/__init__.py
two_fast_auth/core.py
two_fast_auth/middleware.py
two_fast_auth-1.1.0.dist-info/LICENSE
two_fast_auth-1.1.0.dist-info/METADATA
two_fast_auth-1.1.0.dist-info/WHEEL
two_fast_auth-1.1.0.dist-info/top_level.txt
two_fast_auth-1.1.0.dist-info/RECORD
