Metadata-Version: 2.1
Name: two-fast-auth
Version: 1.1.0
Summary: FastAPI 2-Factor Authentication Middleware
Home-page: https://github.com/rennf93/two-fast-auth
Author: Renzo Franceschini
Author-email: rennf93@gmail.com
License: MIT
Keywords: fastapi,security,2fa,authentication,middleware
Classifier: Development Status :: 4 - Beta
Classifier: Framework :: FastAPI
Classifier: Intended Audience :: Developers
Classifier: License :: OSI Approved :: MIT License
Classifier: Operating System :: OS Independent
Classifier: Programming Language :: Python :: 3
Classifier: Topic :: Security
Classifier: Topic :: Software Development :: Libraries :: Python Modules
Requires-Python: >=3.10
License-File: LICENSE
Requires-Dist: fastapi
Requires-Dist: pyotp
Requires-Dist: qrcode
Requires-Dist: pillow
Provides-Extra: dev
Requires-Dist: black; extra == "dev"
Requires-Dist: fastapi-users; extra == "dev"
Requires-Dist: flake8; extra == "dev"
Requires-Dist: httpx; extra == "dev"
Requires-Dist: pytest; extra == "dev"
Requires-Dist: pytest-asyncio; extra == "dev"
Requires-Dist: pytest-cov; extra == "dev"
Requires-Dist: pytest-mock; extra == "dev"
Requires-Dist: sqlalchemy; extra == "dev"
